scikit23/__init__.py
scikit23/reader.py
scikit23-0.1.1.dist-info/METADATA
scikit23-0.1.1.dist-info/WHEEL
scikit23-0.1.1.dist-info/top_level.txt
scikit23-0.1.1.dist-info/RECORD
