Metadata-Version: 2.4
Name: scikit23
Version: 0.1.1
Summary: scikit replica
Author: Johndoe
Requires-Python: >=3.7
Dynamic: author
Dynamic: requires-python
Dynamic: summary
